[
  {
    "query": "Rotate 402-32-11-61-990-802-A by 35 degrees in Y axis",
    "programs": [
      "ExtractNumbers query",
      "SaveVal2Var prev var1",
      "ExtractID figure query",
      "Unique prev",
      "SaveVal2Var prev var2",
      "Same var2 prev",
      "Filter3DAttr name prev root",
      "Unique prev",
      "Rotate prev var1"
    ],
    "reply": "402-32-11-61-990-802-A"
  },
  {
    "query": "Rotate 402-32-11-61-990-802-A by 90 degrees in X axis",
    "programs": [
      "ExtractNumbers query",
      "SaveVal2Var prev var1",
      "ExtractID figure query",
      "Unique prev",
      "SaveVal2Var prev var2",
      "Same var2 prev",
      "Filter3DAttr name prev root",
      "Unique prev",
      "Rotate prev var1"
    ],
    "reply": "402-32-11-61-990-802-A"
  },
  {
    "query": "Scale up 402-32-11-61-990-802-A by 0.5",
    "programs": [
      "ExtractNumbers query",
      "SaveVal2Var prev var1",
      "ExtractID figure query",
      "Unique prev",
      "SaveVal2Var prev var2",
      "Same var2 prev",
      "Filter3DAttr name prev root",
      "Unique prev",
      "Scale up prev var1"
    ],
    "reply": "402-32-11-61-990-802-A"
  },
  {
    "query": "Scale down 402-32-11-61-990-802-A by 2",
    "programs": [
      "ExtractNumbers query",
      "SaveVal2Var prev var1",
      "ExtractID figure query",
      "Unique prev",
      "SaveVal2Var prev var2",
      "Same var2 prev",
      "Filter3DAttr name prev root",
      "Unique prev",
      "Scale down prev var1"
    ],
    "reply": "402-32-11-61-990-802-A"
  },
  {
    "query": "Show highlight [41], [46]",
    "programs": [
      "ExtractNumbers query",
      "SaveVal2Var prev var1",
      "ExtractID object query",
      "SaveVal2Var prev var2",
      "Filter3DAttr name prev root",
      "Highlight on prev"
    ],
    "reply": "[41], [46]"
  },
  {
    "query": "Remove highlight [41], [46]",
    "programs": [
      "ExtractNumbers query",
      "SaveVal2Var prev var1",
      "ExtractID object query",
      "SaveVal2Var prev var2",
      "Filter3DAttr name prev root",
      "Highlight off prev"
    ],
    "reply": "[41], [46]"
  },
  {
    "query": "Animate on 402-32-11-61-990-802-A",
    "programs": [
      "ExtractNumbers query",
      "SaveVal2Var prev var1",
      "ExtractID figure query",
      "Unique prev",
      "SaveVal2Var prev var2",
      "Same var2 prev",
      "Filter3DAttr name prev root",
      "Unique prev",
      "Animate on prev"
    ],
    "reply": "402-32-11-61-990-802-A"
  },
  {
    "query": "Animate off 402-32-11-61-990-802-A",
    "programs": [
      "ExtractNumbers query",
      "SaveVal2Var prev var1",
      "ExtractID figure query",
      "Unique prev",
      "SaveVal2Var prev var2",
      "Same var2 prev",
      "Filter3DAttr name prev root",
      "Unique prev",
      "Animate off prev"
    ],
    "reply": "402-32-11-61-990-802-A"
  },
  {
    "query": "Show left side of figure 402-32-11-61-990-802-A",
    "programs": [
      "ExtractNumbers query",
      "SaveVal2Var prev var1",
      "ExtractID figure query",
      "Unique prev",
      "SaveVal2Var prev var2",
      "Same var2 prev",
      "Filter3DAttr name prev root",
      "Unique prev",
      "ShowSide left prev"
    ],
    "reply": "402-32-11-61-990-802-A"
  },
  {
    "query": "Show top side of figure 402-32-11-61-990-802-A",
    "programs": [
      "ExtractNumbers query",
      "SaveVal2Var prev var1",
      "ExtractID figure query",
      "Unique prev",
      "SaveVal2Var prev var2",
      "Same var2 prev",
      "Filter3DAttr name prev root",
      "Unique prev",
      "ShowSide top prev"
    ],
    "reply": "402-32-11-61-990-802-A"
  },
  {
    "query": "Show bottom side of figure 402-32-11-61-990-802-A",
    "programs": [
      "ExtractNumbers query",
      "SaveVal2Var prev var1",
      "ExtractID figure query",
      "Unique prev",
      "SaveVal2Var prev var2",
      "Same var2 prev",
      "Filter3DAttr name prev root",
      "Unique prev",
      "ShowSide bottom prev"
    ],
    "reply": "402-32-11-61-990-802-A"
  },
  {
    "query": "Show back side of figure 402-32-11-61-990-802-A",
    "programs": [
      "ExtractNumbers query",
      "SaveVal2Var prev var1",
      "ExtractID figure query",
      "Unique prev",
      "SaveVal2Var prev var2",
      "Same var2 prev",
      "Filter3DAttr name prev root",
      "Unique prev",
      "ShowSide back prev"
    ],
    "reply": "402-32-11-61-990-802-A"
  },
  {
    "query": "Hide objects [41], [46] in this figure",
    "programs": [
      "ExtractNumbers query",
      "SaveVal2Var prev var1",
      "ExtractID object query",
      "SaveVal2Var prev var2",
      "Filter3DAttr name prev root",
      "Visibility off prev"
    ],
    "reply": "[41], [46]"
  },
  {
    "query": "Make visible objects [41], [46] in this figure",
    "programs": [
      "ExtractNumbers query",
      "SaveVal2Var prev var1",
      "ExtractID object query",
      "SaveVal2Var prev var2",
      "Filter3DAttr name prev root",
      "Visibility on prev"
    ],
    "reply": "[41], [46]"
  },
  {
    "query": "Show close look of objects [41], [46]",
    "programs": [
      "ExtractNumbers query",
      "SaveVal2Var prev var1",
      "ExtractID object query",
      "SaveVal2Var prev var2",
      "Filter3DAttr name prev root",
      "CloseLook prev"
    ],
    "reply": "[41], [46]"
  },
  {
    "query": "Show close look of objects [8], [43], [44], [46]",
    "programs": [
      "ExtractNumbers query",
      "SaveVal2Var prev var1",
      "ExtractID object query",
      "SaveVal2Var prev var2",
      "Filter3DAttr name prev root",
      "CloseLook prev"
    ],
    "reply": "[8], [43], [44], [46]"
  },
  {
    "query": "Show Side By Side view of items in figure 402-32-11-61-990-802-A",
    "programs": [
      "ExtractNumbers query",
      "SaveVal2Var prev var1",
      "ExtractID figure query",
      "Unique prev",
      "SaveVal2Var prev var2",
      "Same var2 prev",
      "Filter3DAttr name prev root",
      "Unique prev",
      "SideBySideLook prev"
    ],
    "reply": "402-32-11-61-990-802-A"
  },
  {
    "query": "Reset 402-32-11-61-990-802-A",
    "programs": [
      "ExtractNumbers query",
      "SaveVal2Var prev var1",
      "ExtractID figure query",
      "Unique prev",
      "SaveVal2Var prev var2",
      "Same var2 prev",
      "Filter3DAttr name prev root",
      "Unique prev",
      "Reset prev"
    ],
    "reply": "402-32-11-61-990-802-A"
  }
]